Forecasting/__init__.py
Forecasting/forecast.py
forecastify-0.1.dist-info/METADATA
forecastify-0.1.dist-info/WHEEL
forecastify-0.1.dist-info/entry_points.txt
forecastify-0.1.dist-info/top_level.txt
forecastify-0.1.dist-info/RECORD
