Metadata-Version: 2.1
Name: forecastify
Version: 0.1
Summary: A package for time series forecasting using ARIMA, SARIMA, and Exponential Smoothing
Home-page: https://github.com/Wasiue03/Forecasting-Python-Package
Author: Abdul Wasiue
Author-email: abdulwasiueunk@gmail.com
License: UNKNOWN
Platform: UNKNOWN
Requires-Python: >=3.7
Requires-Dist: pandas
Requires-Dist: statsmodels
Requires-Dist: optuna
Requires-Dist: matplotlib
Requires-Dist: numpy
Requires-Dist: scikit-learn
